menousdb_python/__init__.py
menousdb_python-0.1.1.dist-info/METADATA
menousdb_python-0.1.1.dist-info/WHEEL
menousdb_python-0.1.1.dist-info/top_level.txt
menousdb_python-0.1.1.dist-info/RECORD
